portakal/__init__.py
portakal/__main__.py
portakal/juicer.py
portakal-0.0.4.dist-info/METADATA
portakal-0.0.4.dist-info/WHEEL
portakal-0.0.4.dist-info/entry_points.txt
portakal-0.0.4.dist-info/top_level.txt
portakal-0.0.4.dist-info/RECORD
