Metadata-Version: 2.2
Name: portakal
Version: 0.0.4
Dynamic: description
Dynamic: description-content-type
